PoetryStudy/data/__init__.py
PoetryStudy/data/core.py
PoetryStudy/py/__init__.py
poetrystudy_py-0.1.5.dist-info/METADATA
poetrystudy_py-0.1.5.dist-info/WHEEL
poetrystudy_py-0.1.5.dist-info/RECORD
