Metadata-Version: 2.1
Name: PoetryStudy.PY
Version: 0.1.5
Summary: 
Author: 解大劦
Author-email: 9727005@qq.com
Requires-Python: >=3.12,<4.0
Classifier: Programming Language :: Python :: 3
Classifier: Programming Language :: Python :: 3.12
Requires-Dist: BasicLibrary.PY (>=0.6.1,<0.7.0)
